arip-1.0.2.dist-info/top_level.txt
arip-1.0.2.dist-info/DESCRIPTION.rst
arip-1.0.2.dist-info/METADATA
arip-1.0.2.dist-info/WHEEL
arip-1.0.2.dist-info/RECORD
arip-1.0.2.dist-info/metadata.json
arip/arip.py
arip/__init__.py
