Metadata-Version: 2.0
Name: arip
Version: 1.0.2
Summary: ARIP, software to quantify bacterial resistance to antibiotics by analysing picture of phenotypic plates
Home-page: https://github.com/mazeitor/antibiotic-resistance-image-process
Author: oriol mazariegos
Author-email: mazeitor@gmail.com
License: GPLv3
Keywords: medical image processing antibiotic resistance phenotypic plate
Platform: UNKNOWN
Classifier: Development Status :: 3 - Alpha
Classifier: Intended Audience :: Science/Research
Classifier: Topic :: Software Development
Classifier: Topic :: Scientific/Engineering :: Image Recognition
Classifier: Topic :: Scientific/Engineering :: Bio-Informatics
Classifier: Topic :: Scientific/Engineering :: Medical Science Apps.
Classifier: License :: OSI Approved :: GNU General Public License v3 or later (GPLv3+)
Classifier: Programming Language :: Python :: 2
Classifier: Programming Language :: Python :: 2.6
Classifier: Programming Language :: Python :: 2.7
